immersim/__init__.py
immersim/checkpoints.py
immersim/enable_checkpoints.py
immersim/items.py
immersim/states.py
immersim/utils.py
immersim-1.1.0.dist-info/licenses/LICENSE
immersim-1.1.0.dist-info/METADATA
immersim-1.1.0.dist-info/WHEEL
immersim-1.1.0.dist-info/top_level.txt
immersim-1.1.0.dist-info/RECORD
