Metadata-Version: 2.4
Name: immersim
Version: 1.1.0
Summary: Immersive Simulations for Jupyter Notebooks
Author: Zubin Kane
License-Expression: MIT
Project-URL: Homepage, https://github.com/Sclamy/ImmersiveSimulations
Project-URL: Issues, https://github.com/Sclamy/ImmersiveSimulations/issues
Classifier: Programming Language :: Python :: 3
Classifier: Operating System :: OS Independent
Requires-Python: >=3.10
License-File: LICENSE
Requires-Dist: dill>=0.4.0
Requires-Dist: ipynbname~=2024.1.0.0
Requires-Dist: notebook>=7.4.5
Requires-Dist: jupyter_server>=2.16.0
Requires-Dist: ipython~=9.4.0
Dynamic: license-file
